StreetSolarTrack/ __init__.py
StreetSolarTrack/utils/__init__.py
StreetSolarTrack/utils/photo.py
StreetSolarTrack/utils/utils.py
streetsolartrack-0.0.8.dist-info/METADATA
streetsolartrack-0.0.8.dist-info/WHEEL
streetsolartrack-0.0.8.dist-info/RECORD
