Metadata-Version: 2.3
Name: StreetSolarTrack
Version: 0.0.8
Summary: A Street View Image Processing and Solar Loaction package
Project-URL: Homepage, https://github.com/GIStudio/StreetSolarTrack
Project-URL: Issues, https://github.com/GIStudio/StreetSolarTrack/issues
Author-email: Shiqi Wang <qtec@outlook.com>
Classifier: Operating System :: OS Independent
Classifier: Programming Language :: Python :: 3
Requires-Python: >=3.8
Requires-Dist: pillow>=10.0.1
